my_openapi_fetcher/__init__.py
my_openapi_fetcher/cli.py
my_openapi_fetcher/main.py
my_fastapi-0.1.0.dist-info/METADATA
my_fastapi-0.1.0.dist-info/WHEEL
my_fastapi-0.1.0.dist-info/entry_points.txt
my_fastapi-0.1.0.dist-info/RECORD
