Metadata-Version: 2.3
Name: my-fastapi
Version: 0.1.0
Summary: 
Author: lee gyu yeol-mac
Author-email: i1004gy@gmail.com
Requires-Python: >=3.10
Classifier: Programming Language :: Python :: 3
Classifier: Programming Language :: Python :: 3.10
Classifier: Programming Language :: Python :: 3.11
Classifier: Programming Language :: Python :: 3.12
Classifier: Programming Language :: Python :: 3.13
Requires-Dist: click (>=8.2.1,<9.0.0)
Requires-Dist: fastapi (>=0.115.14,<0.116.0)
Requires-Dist: httpx (>=0.28.1,<0.29.0)
Requires-Dist: setuptools (>=80.9.0,<81.0.0)
Requires-Dist: uvicorn[standard] (>=0.35.0,<0.36.0)
Requires-Dist: wheel (>=0.45.1,<0.46.0)
